pyMV2H/__init__.py
pyMV2H/__main__.py
pyMV2H/cli.py
pyMV2H/commands/__init__.py
pyMV2H/commands/base.py
pyMV2H/commands/compare_files.py
pyMV2H/commands/midi_converter.py
pyMV2H/converter/__init__.py
pyMV2H/converter/base.py
pyMV2H/converter/midi_converter.py
pyMV2H/metrics/__init__.py
pyMV2H/metrics/f1.py
pyMV2H/metrics/harmony.py
pyMV2H/metrics/meter.py
pyMV2H/metrics/multi_pitch.py
pyMV2H/metrics/mv2h.py
pyMV2H/metrics/note_value.py
pyMV2H/metrics/voice.py
pyMV2H/utils/__init__.py
pyMV2H/utils/algorithm_config.py
pyMV2H/utils/align_files.py
pyMV2H/utils/alignment_node.py
pyMV2H/utils/comparators.py
pyMV2H/utils/convert_time.py
pyMV2H/utils/freeze_args.py
pyMV2H/utils/matches.py
pyMV2H/utils/midi_meta_tonic_map.py
pyMV2H/utils/music.py
pyMV2H/utils/mv2h.py
pyMV2H/utils/normalize_list_size.py
pyMV2H/utils/pojos.py
pyMV2H/utils/remove_duplicates.py
pyMV2H/utils/voice.py
pyMV2H-1.1.0.dist-info/METADATA
pyMV2H-1.1.0.dist-info/WHEEL
pyMV2H-1.1.0.dist-info/entry_points.txt
pyMV2H-1.1.0.dist-info/top_level.txt
pyMV2H-1.1.0.dist-info/RECORD
