Metadata-Version: 2.1
Name: pyMV2H
Version: 1.1.0
Summary: A python implementation of MV2H metric
Home-page: https://github.com/lucasmpaim/pyMV2H
Author: Lucas Mrowskovsky Paim
Author-email: lucas.mrowskovsky@pucpr.edu.br
License: UNLICENSE
Keywords: cli
Requires-Dist: docopt
Requires-Dist: pretty-midi
Requires-Dist: mido
Requires-Dist: tqdm
Provides-Extra: test
Requires-Dist: coverage ; extra == 'test'
Requires-Dist: pytest ; extra == 'test'
Requires-Dist: pytest-cov ; extra == 'test'
